vasp/__init__.py
vasp/calculator.py
vasp/cli.py
vasp/exceptions.py
vasp/parameters.py
vasp/database/__init__.py
vasp/database/embedders.py
vasp/database/vector_db.py
vasp/mixins/__init__.py
vasp/mixins/analysis.py
vasp/mixins/dynamics.py
vasp/mixins/electronic.py
vasp/mixins/io.py
vasp/recipes/__init__.py
vasp/recipes/core.py
vasp/recipes/decorators.py
vasp/recipes/phonons.py
vasp/recipes/slabs.py
vasp/runners/__init__.py
vasp/runners/base.py
vasp/runners/interactive.py
vasp/runners/kubernetes.py
vasp/runners/local.py
vasp/runners/mock.py
vasp/runners/slurm.py
vasp/runners/socket_io.py
vasp/tests/__init__.py
vasp/tests/conftest.py
vasp/tests/test_analysis.py
vasp/tests/test_calculator.py
vasp/tests/test_database.py
vasp/tests/test_exceptions.py
vasp/tests/test_interactive.py
vasp/tests/test_mixins.py
vasp/tests/test_parameters.py
vasp/tests/test_recipes.py
vasp/tests/test_runners.py
vasp/tests/test_socket_io.py
vasp/tests/test_vector_database.py
vasp/tests/fixtures/__init__.py
vasp_ase-2.0.0.dist-info/METADATA
vasp_ase-2.0.0.dist-info/WHEEL
vasp_ase-2.0.0.dist-info/entry_points.txt
vasp_ase-2.0.0.dist-info/licenses/LICENSE
vasp_ase-2.0.0.dist-info/RECORD
