Metadata-Version: 2.4
Name: vasp-ase
Version: 2.0.0
Summary: Modern ASE calculator interface for VASP with workflow integration
Project-URL: Homepage, https://github.com/jkitchin/vasp
Project-URL: Documentation, https://github.com/jkitchin/vasp#readme
Project-URL: Repository, https://github.com/jkitchin/vasp.git
Project-URL: Issues, https://github.com/jkitchin/vasp/issues
Author-email: John Kitchin <jkitchin@andrew.cmu.edu>
License-Expression: MIT
License-File: LICENSE
Keywords: ase,automation,computational-chemistry,dft,machine-learning,materials-science,phonons,vasp,workflow
Classifier: Development Status :: 4 - Beta
Classifier: Intended Audience :: Science/Research
Classifier: License :: OSI Approved :: MIT License
Classifier: Operating System :: OS Independent
Classifier: Programming Language :: Python :: 3
Classifier: Programming Language :: Python :: 3.9
Classifier: Programming Language :: Python :: 3.10
Classifier: Programming Language :: Python :: 3.11
Classifier: Programming Language :: Python :: 3.12
Classifier: Programming Language :: Python :: 3.13
Classifier: Topic :: Scientific/Engineering :: Chemistry
Classifier: Topic :: Scientific/Engineering :: Physics
Requires-Python: >=3.9
Requires-Dist: ase>=3.22
Requires-Dist: numpy>=1.22
Requires-Dist: scipy>=1.8
Provides-Extra: all
Requires-Dist: build>=1.0; extra == 'all'
Requires-Dist: jupyter-book>=1.0.0; extra == 'all'
Requires-Dist: kubernetes>=28.0; extra == 'all'
Requires-Dist: matplotlib>=3.5; extra == 'all'
Requires-Dist: mypy>=1.0; extra == 'all'
Requires-Dist: myst-nb>=1.0.0; extra == 'all'
Requires-Dist: phonopy>=2.20; extra == 'all'
Requires-Dist: pytest-cov>=4.0; extra == 'all'
Requires-Dist: pytest>=7.0; extra == 'all'
Requires-Dist: ruff>=0.1; extra == 'all'
Requires-Dist: sphinx-autodoc-typehints>=2.0.0; extra == 'all'
Requires-Dist: sphinx-design>=0.5.0; extra == 'all'
Requires-Dist: sphinx>=7.0.0; extra == 'all'
Requires-Dist: sphinxcontrib-bibtex>=2.6.0; extra == 'all'
Requires-Dist: twine>=4.0; extra == 'all'
Provides-Extra: dev
Requires-Dist: build>=1.0; extra == 'dev'
Requires-Dist: mypy>=1.0; extra == 'dev'
Requires-Dist: pytest-cov>=4.0; extra == 'dev'
Requires-Dist: pytest>=7.0; extra == 'dev'
Requires-Dist: ruff>=0.1; extra == 'dev'
Requires-Dist: twine>=4.0; extra == 'dev'
Provides-Extra: docs
Requires-Dist: jupyter-book>=1.0.0; extra == 'docs'
Requires-Dist: myst-nb>=1.0.0; extra == 'docs'
Requires-Dist: sphinx-autodoc-typehints>=2.0.0; extra == 'docs'
Requires-Dist: sphinx-design>=0.5.0; extra == 'docs'
Requires-Dist: sphinx>=7.0.0; extra == 'docs'
Requires-Dist: sphinxcontrib-bibtex>=2.6.0; extra == 'docs'
Provides-Extra: kubernetes
Requires-Dist: kubernetes>=28.0; extra == 'kubernetes'
Provides-Extra: phonons
Requires-Dist: phonopy>=2.20; extra == 'phonons'
Provides-Extra: plotting
Requires-Dist: matplotlib>=3.5; extra == 'plotting'
Provides-Extra: slurm
Provides-Extra: workflows
